miracle/__init__.py
miracle/batch.py
miracle/client.py
miracle/core.py
miracle_sdk-0.1.1.dist-info/METADATA
miracle_sdk-0.1.1.dist-info/WHEEL
miracle_sdk-0.1.1.dist-info/licenses/LICENSE
miracle_sdk-0.1.1.dist-info/RECORD
