Metadata-Version: 2.4
Name: miracle-sdk
Version: 0.1.1
Summary: The Official Python SDK for the MIRACLE API - Cardiovascular MRI Reference Values
Project-URL: Homepage, https://github.com/drankush/MIRACLE-sdk
Project-URL: Bug Tracker, https://github.com/drankush/MIRACLE-sdk/issues
Project-URL: Documentation, https://miracleapi.readme.io
Author-email: Ankush <miracle-support@drankush.com>
License: MIT License
License-File: LICENSE
Keywords: cardiovascular,medical-imaging,mri,pediatrics,reference-values,scmr,sdk,z-score
Classifier: Development Status :: 4 - Beta
Classifier: Intended Audience :: Healthcare Industry
Classifier: Intended Audience :: Science/Research
Classifier: License :: OSI Approved :: MIT License
Classifier: Programming Language :: Python :: 3
Classifier: Topic :: Scientific/Engineering :: Medical Science Apps.
Requires-Python: >=3.8
Requires-Dist: pandas>=1.3.0
Requires-Dist: pyyaml>=6.0
Requires-Dist: requests>=2.25.0
Provides-Extra: dev
Requires-Dist: black; extra == 'dev'
Requires-Dist: mypy; extra == 'dev'
Requires-Dist: pytest; extra == 'dev'
Requires-Dist: types-pyyaml; extra == 'dev'
Requires-Dist: types-requests; extra == 'dev'
